{
  "DateHumanize_SingleSecondAgo": "1 秒鐘前",
  "DateHumanize_MultipleSecondsAgo": "{0} 秒鐘前",
  "DateHumanize_SingleMinuteAgo": "1 分鐘前",
  "DateHumanize_MultipleMinutesAgo": "{0} 分鐘前",
  "DateHumanize_SingleHourAgo": "1 小時前",
  "DateHumanize_MultipleHoursAgo": "{0} 小時前",
  "DateHumanize_SingleDayAgo": "昨天",
  "DateHumanize_MultipleDaysAgo": "{0} 天前",
  "DateHumanize_SingleMonthAgo": "1 個月前",
  "DateHumanize_MultipleMonthsAgo": "{0} 個月前",
  "DateHumanize_SingleYearAgo": "去年",
  "DateHumanize_MultipleYearsAgo": "{0} 年前",
  "TimeSpanHumanize_MultipleDays": "{0} 天",
  "TimeSpanHumanize_MultipleHours": "{0} 小時",
  "TimeSpanHumanize_MultipleMilliseconds": "{0} 毫秒",
  "TimeSpanHumanize_MultipleMinutes": "{0} 分",
  "TimeSpanHumanize_MultipleSeconds": "{0} 秒",
  "TimeSpanHumanize_SingleDay": "1 天",
  "TimeSpanHumanize_SingleHour": "1 小時",
  "TimeSpanHumanize_SingleMillisecond": "1 毫秒",
  "TimeSpanHumanize_SingleMinute": "1 分",
  "TimeSpanHumanize_SingleSecond": "1 秒",
  "TimeSpanHumanize_Zero": "沒有時間",
  "TimeSpanHumanize_MultipleWeeks": "{0} 周",
  "TimeSpanHumanize_SingleWeek": "1 周",
  "DateHumanize_MultipleDaysFromNow": "{0} 天後",
  "DateHumanize_MultipleHoursFromNow": "{0} 小時後",
  "DateHumanize_MultipleMinutesFromNow": "{0} 分鐘後",
  "DateHumanize_MultipleMonthsFromNow": "{0} 個月後",
  "DateHumanize_MultipleSecondsFromNow": "{0} 秒鐘後",
  "DateHumanize_MultipleYearsFromNow": "{0} 年後",
  "DateHumanize_Now": "今天",
  "DateHumanize_SingleDayFromNow": "明天",
  "DateHumanize_SingleHourFromNow": "1 小時後",
  "DateHumanize_SingleMinuteFromNow": "1 分鐘後",
  "DateHumanize_SingleMonthFromNow": "1 個月後",
  "DateHumanize_SingleSecondFromNow": "1 秒鐘後",
  "DateHumanize_SingleYearFromNow": "明年",
  "TimeSpanHumanize_MultipleMonths": "{0} 個月",
  "TimeSpanHumanize_MultipleYears": "{0} 年",
  "TimeSpanHumanize_SingleMonth": "1 個月",
  "TimeSpanHumanize_SingleYear": "1 年"
}